fluidsynth.py
pyFluidSynth-1.3.2.dist-info/LICENSE
pyFluidSynth-1.3.2.dist-info/METADATA
pyFluidSynth-1.3.2.dist-info/WHEEL
pyFluidSynth-1.3.2.dist-info/top_level.txt
pyFluidSynth-1.3.2.dist-info/RECORD
