Metadata-Version: 2.1
Name: pyFluidSynth
Version: 1.3.2
Summary: Python bindings for FluidSynth, a MIDI synthesizer that uses SoundFont instruments
Home-page: https://github.com/nwhitehead/pyfluidsynth
Author: Nathan Whitehead
Author-email: nwhitehe@gmail.com
License-File: LICENSE
Requires-Dist: numpy
